{"LINKED": [{"LAT": "-39.62341", "LON": "-14.87223", "SPEED": "156", "COURSE": "172", "HEADING": "172", "ELAPSED": 1606493940.0, "SHIPNAME": "[SAT-AIS]", "SHIPTYPE": "9", "TYPE_IMG": "9", "TYPE_NAME": "Pleasure Craft", "STATUS_NAME": "Unknown"}, {"LAT": "-39.62341", "LON": "-14.87223", "SPEED": "156", "COURSE": "172", "HEADING": "172", "ELAPSED": 1606493940.0, "SHIPNAME": "[SAT-AIS]", "SHIPTYPE": "9", "TYPE_IMG": "9", "TYPE_NAME": "Pleasure Craft", "STATUS_NAME": "Unknown"}, {"LAT": "-39.74165", "LON": "-14.87154", "SPEED": "141", "COURSE": "188", "HEADING": "188", "ELAPSED": 1606498440.0, "SHIPNAME": "[SAT-AIS]", "SHIPTYPE": "9", "TYPE_IMG": "9", "TYPE_NAME": "Pleasure Craft", "STATUS_NAME": "Unknown"}], "APIVIA": [{"LAT": "-42.31216", "LON": "-8.750023", "SPEED": "203", "COURSE": "158", "HEADING": "158", "ELAPSED": 1606493940.0, "SHIPNAME": "[SAT-AIS]", "SHIPTYPE": "9", "TYPE_IMG": "9", "TYPE_NAME": "Pleasure Craft", "STATUS_NAME": "Unknown"}, {"LAT": "-42.31216", "LON": "-8.750023", "SPEED": "203", "COURSE": "158", "HEADING": "158", "ELAPSED": 1606493940.0, "SHIPNAME": "[SAT-AIS]", "SHIPTYPE": "9", "TYPE_IMG": "9", "TYPE_NAME": "Pleasure Craft", "STATUS_NAME": "Unknown"}, {"LAT": "-42.48757", "LON": "-8.660283", "SPEED": "255", "COURSE": "156", "HEADING": "156", "ELAPSED": 1606498560.0, "SHIPNAME": "[SAT-AIS]", "SHIPTYPE": "9", "TYPE_IMG": "9", "TYPE_NAME": "Pleasure Craft", "STATUS_NAME": "Unknown"}], "CAM": [{"LAT": "-36.54325", "LON": "-14.01889", "SPEED": "152", "COURSE": "99", "HEADING": "99", "ELAPSED": 1606493820.0, "SHIPNAME": "[SAT-AIS]", "SHIPTYPE": "9", "TYPE_IMG": "9", "TYPE_NAME": "Pleasure Craft", "STATUS_NAME": "Unknown"}, {"LAT": "-36.54325", "LON": "-14.01889", "SPEED": "152", "COURSE": "99", "HEADING": "99", "ELAPSED": 1606493820.0, "SHIPNAME": "[SAT-AIS]", "SHIPTYPE": "9", "TYPE_IMG": "9", "TYPE_NAME": "Pleasure Craft", "STATUS_NAME": "Unknown"}, {"LAT": "-36.488", "LON": "-14.28544", "SPEED": "149", "COURSE": "109", "HEADING": "109", "ELAPSED": 1606497540.0, "SHIPNAME": "[SAT-AIS]", "SHIPTYPE": "9", "TYPE_IMG": "9", "TYPE_NAME": "Pleasure Craft", "STATUS_NAME": "Unknown"}]}